src/umls_client_jamiesprax/__init__.py
src/umls_client_jamiesprax/umls_client.py
venv/bin/activate_this.py
venv/bin/rst2html.py
venv/bin/rst2html4.py
venv/bin/rst2html5.py
venv/bin/rst2latex.py
venv/bin/rst2man.py
venv/bin/rst2odt.py
venv/bin/rst2odt_prepstyles.py
venv/bin/rst2pseudoxml.py
venv/bin/rst2s5.py
venv/bin/rst2xetex.py
venv/bin/rst2xml.py
venv/bin/rstpep2html.py
venv/lib/python3.8/site-packages/_virtualenv.py
venv/lib/python3.8/site-packages/six.py
venv/lib/python3.8/site-packages/typing_extensions.py
venv/lib/python3.8/site-packages/zipp.py
venv/lib/python3.8/site-packages/_distutils_hack/__init__.py
venv/lib/python3.8/site-packages/_distutils_hack/override.py
venv/lib/python3.8/site-packages/bleach/__init__.py
venv/lib/python3.8/site-packages/bleach/callbacks.py
venv/lib/python3.8/site-packages/bleach/css_sanitizer.py
venv/lib/python3.8/site-packages/bleach/html5lib_shim.py
venv/lib/python3.8/site-packages/bleach/linkifier.py
venv/lib/python3.8/site-packages/bleach/parse_shim.py
venv/lib/python3.8/site-packages/bleach/sanitizer.py
venv/lib/python3.8/site-packages/bleach/_vendor/__init__.py
venv/lib/python3.8/site-packages/bleach/_vendor/parse.py
venv/lib/python3.8/site-packages/bleach/_vendor/html5lib/__init__.py
venv/lib/python3.8/site-packages/bleach/_vendor/html5lib/_ihatexml.py
venv/lib/python3.8/site-packages/bleach/_vendor/html5lib/_inputstream.py
venv/lib/python3.8/site-packages/bleach/_vendor/html5lib/_tokenizer.py
venv/lib/python3.8/site-packages/bleach/_vendor/html5lib/_utils.py
venv/lib/python3.8/site-packages/bleach/_vendor/html5lib/constants.py
venv/lib/python3.8/site-packages/bleach/_vendor/html5lib/html5parser.py
venv/lib/python3.8/site-packages/bleach/_vendor/html5lib/serializer.py
venv/lib/python3.8/site-packages/bleach/_vendor/html5lib/_trie/__init__.py
venv/lib/python3.8/site-packages/bleach/_vendor/html5lib/_trie/_base.py
venv/lib/python3.8/site-packages/bleach/_vendor/html5lib/_trie/py.py
umls_client-0.1.0.dist-info/METADATA
umls_client-0.1.0.dist-info/WHEEL
umls_client-0.1.0.dist-info/entry_points.txt
umls_client-0.1.0.dist-info/license_files/LICENSE
umls_client-0.1.0.dist-info/RECORD
