Metadata-Version: 2.1
Name: umls-client
Version: 0.1.0
Summary: A light umls client with rate limiting
Project-URL: Bug Tracker, https://gitlab.com/jamiesprax/umls-client/-/issues
Project-URL: Homepage, https://gitlab.com/jamiesprax/umls-client
Author-email: Jamie C <jamiesprax@gmail.com>
License: MIT License
Classifier: License :: OSI Approved :: MIT License
Classifier: Operating System :: OS Independent
Classifier: Programming Language :: Python :: 3
Requires-Python: >=3.7
